code_inspector/__init__.py
code_inspector/__main__.py
code_inspector/analyze.py
code_inspector/check_quality.py
code_inspector/common.py
code_inspector/compare.py
code_inspector/constants.py
code_inspector/github_action.py
code_inspector/pre_hook_check.py
code_inspector/project.py
code_inspector/version.py
code_inspector/exceptions/__init__.py
code_inspector/exceptions/git_command_exception.py
code_inspector/graphql/__init__.py
code_inspector/graphql/common.py
code_inspector/graphql/constants.py
code_inspector/graphql/file_analysis.py
code_inspector/graphql/project.py
code_inspector/model/__init__.py
code_inspector/model/violation.py
code_inspector/utils/__init__.py
code_inspector/utils/file_utils.py
code_inspector/utils/git.py
code_inspector/utils/patch_utils.py
code_inspector/utils/violation_utils.py
code_inspector-0.0.18.dist-info/LICENSE
code_inspector-0.0.18.dist-info/METADATA
code_inspector-0.0.18.dist-info/WHEEL
code_inspector-0.0.18.dist-info/entry_points.txt
code_inspector-0.0.18.dist-info/top_level.txt
code_inspector-0.0.18.dist-info/RECORD
