Metadata-Version: 2.1
Name: code-inspector
Version: 0.0.18
Summary: Trigger new code analysis on code-inspector.io
Home-page: https://github.com/codeinspectorio/citool
Author: code-inspector
License: BSD
Project-URL: Changelog, https://github.com/codeinspectorio/citool/blob/master/CHANGELOG.md
Project-URL: Docs, https://github.com/codeinspectorio/citool/
Platform: UNKNOWN
Classifier: Development Status :: 5 - Production/Stable
Classifier: Topic :: Software Development :: Testing
Classifier: Intended Audience :: Developers
Classifier: License :: OSI Approved :: BSD License
Classifier: Operating System :: OS Independent
Classifier: Programming Language :: Python
Classifier: Programming Language :: Python :: 3.5
Classifier: Programming Language :: Python :: 3.6
Classifier: Programming Language :: Python :: 3.7
Classifier: Programming Language :: Python :: Implementation :: CPython
Classifier: Programming Language :: Python :: Implementation :: PyPy
License-File: LICENSE
Requires-Dist: docopt (>=0.6.2)
Requires-Dist: requests (>=2.25.1)
Requires-Dist: unidiff (>=0.6.0)
Requires-Dist: tenacity (>=7.0.0)
Requires-Dist: urllib3[secure] ; python_version < "3"
Provides-Extra: yaml
Requires-Dist: PyYAML (>=3.10) ; extra == 'yaml'
